gatsbie/__init__.py
gatsbie/client.py
gatsbie/errors.py
gatsbie/types.py
gatsbie/target/__init__.py
gatsbie/target/client.py
gatsbie/target/errors.py
gatsbie/target/types.py
gatsbie-1.0.6.dist-info/METADATA
gatsbie-1.0.6.dist-info/WHEEL
gatsbie-1.0.6.dist-info/RECORD
