Metadata-Version: 2.4
Name: gatsbie
Version: 1.0.6
Summary: Official Python SDK for the Gatsbie Captcha API
Project-URL: Homepage, https://gatsbie.io
Project-URL: Documentation, https://docs.gatsbie.io
Project-URL: Repository, https://github.com/jaygatsbie/sdk-python
Author-email: Gatsbie <support@gatsbie.io>
License-Expression: MIT
Keywords: akamai,captcha,cloudflare,datadome,recaptcha,turnstile
Classifier: Development Status :: 5 - Production/Stable
Classifier: Intended Audience :: Developers
Classifier: License :: OSI Approved :: MIT License
Classifier: Operating System :: OS Independent
Classifier: Programming Language :: Python :: 3
Classifier: Programming Language :: Python :: 3.8
Classifier: Programming Language :: Python :: 3.9
Classifier: Programming Language :: Python :: 3.10
Classifier: Programming Language :: Python :: 3.11
Classifier: Programming Language :: Python :: 3.12
Classifier: Typing :: Typed
Requires-Python: >=3.8
Requires-Dist: httpx>=0.24.0
Provides-Extra: dev
Requires-Dist: pytest-asyncio>=0.21.0; extra == 'dev'
Requires-Dist: pytest>=7.0.0; extra == 'dev'
